<?xml version="1.0" encoding="utf-8"?>
<Defs>

	<CultivaRim.CropColumnDef Name="CultivaRim_CropLabel">
		<defName>CultivaRim_Label</defName>
		<workerClass>CultivaRim.CropColumnWorker_Label</workerClass>
		<widthPriority>100</widthPriority>
	</CultivaRim.CropColumnDef>

	<CultivaRim.CropColumnDef Name="CultivaRim_CropLabelWithIcon" ParentName="CultivaRim_CropLabel">
		<defName>CultivaRim_LabelWithIcon</defName>
		<showIcon>true</showIcon>
	</CultivaRim.CropColumnDef>

	<CultivaRim.CropColumnDef>
		<defName>CultivaRim_Level</defName>
		<label>level</label>
		<workerClass>CultivaRim.CropColumnWorker_Level</workerClass>
		<sortable>true</sortable>
		<width>30</width>
	</CultivaRim.CropColumnDef>

	<CultivaRim.CropColumnDef>
		<defName>CultivaRim_Experience</defName>
		<label>experience</label>
		<workerClass>CultivaRim.CropColumnWorker_Experience</workerClass>
	</CultivaRim.CropColumnDef>

	<CultivaRim.CropColumnDef>
		<defName>CultivaRim_ProductYield</defName>
		<label>yield</label>
		<workerClass>CultivaRim.CropColumnWorker_StatProductYield</workerClass>
		<width>30</width>
	</CultivaRim.CropColumnDef>

	<CultivaRim.CropColumnDef>
		<defName>CultivaRim_GrowthSpeed</defName>
		<label>growth</label>
		<workerClass>CultivaRim.CropColumnWorker_StatGrowthSpeed</workerClass>
		<width>30</width>
	</CultivaRim.CropColumnDef>

	<CultivaRim.CropColumnDef>
		<defName>CultivaRim_HeatResist</defName>
		<label>heat</label>
		<workerClass>CultivaRim.CropColumnWorker_StatHeatResist</workerClass>
		<width>30</width>
	</CultivaRim.CropColumnDef>

	<CultivaRim.CropColumnDef>
		<defName>CultivaRim_ColdResist</defName>
		<label>cold</label>
		<workerClass>CultivaRim.CropColumnWorker_StatColdResist</workerClass>
		<width>30</width>
	</CultivaRim.CropColumnDef>

</Defs>